persona_agent/__init__.py
persona_agent/core.py
persona_agent/lite_llm.py
persona_agent/memory.py
persona_agent/profiles.py
persona_agent/py.typed
persona_agent/skills.py
persona_agent-0.1.2.dist-info/WHEEL
persona_agent-0.1.2.dist-info/METADATA
persona_agent-0.1.2.dist-info/RECORD
