Metadata-Version: 2.4
Name: persona-agent
Version: 0.1.2
Summary: PersonaAgent: a configurable, persona-based LLM agent wrapper with memory, skills, and adaptive behavior.
Author: littledumb
Author-email: littledumb <littledumb@dumbsmart.org>
License-Expression: MIT
Requires-Dist: litellm>=1.80.7
Requires-Python: >=3.9
Project-URL: Homepage, https://github.com/dumbsmart-org/persona-agent
Project-URL: Issues, https://github.com/dumbsmart-org/persona-agent/issues
Project-URL: Repository, https://github.com/dumbsmart-org/persona-agent.git
